aws_lambda_cask-0.1.1.dist-info/licenses/LICENSE
lambda_cask/__init__.py
lambda_cask/wsgi.py
aws_lambda_cask-0.1.1.dist-info/METADATA
aws_lambda_cask-0.1.1.dist-info/WHEEL
aws_lambda_cask-0.1.1.dist-info/top_level.txt
aws_lambda_cask-0.1.1.dist-info/RECORD
