Metadata-Version: 2.4
Name: aws-lambda-cask
Version: 0.1.1
Summary: Wrapper to enable usage of Python WSGI frameworks within AWS Lambda environments.
Home-page: https://github.com/pilate/aws-lambda-cask
License: MIT License
License-File: LICENSE
Dynamic: license-file
